{
    "crowdin": {
        "ar": [],
        "ca": [],
        "de": [],
        "es-ES": [
            "thegamerrr",
            "davidj77",
            "martimiguel2000",
            "MRGABOZ"
        ],
        "fi": [],
        "fr": [],
        "id": [],
        "it": [
            "Veronika191",
            "Mattyy_"
        ],
        "ja": [],
        "ko": [],
        "nl": [],
        "pl": [],
        "pt-PT": [
            "DaRkNeSs9923",
            "ijonasz"
        ],
        "ru": [
            "chinnhau"
        ],
        "sr": [],
        "sv": [],
        "tr": [
            "ByJoker33"
        ],
        "uk": [],
        "uz": [],
        "zh-CN": [
            "yiteei"
        ]
    },
    "github": [
        {
            "name": "ImOnlyFire",
            "avatar": "https://avatars.githubusercontent.com/u/56583784?v=4"
        },
        {
            "name": "null-nick",
            "avatar": "https://avatars.githubusercontent.com/u/64551534?v=4"
        },
        {
            "name": "xaxtix",
            "avatar": "https://avatars.githubusercontent.com/u/7038595?v=4"
        },
        {
            "name": "DrKLO",
            "avatar": "https://avatars.githubusercontent.com/u/69369?v=4"
        },
        {
            "name": "jsonchi",
            "avatar": "https://avatars.githubusercontent.com/u/3435533?v=4"
        },
        {
            "name": "alabiaga",
            "avatar": "https://avatars.githubusercontent.com/u/494160?v=4"
        },
        {
            "name": "zhukov",
            "avatar": "https://avatars.githubusercontent.com/u/775173?v=4"
        },
        {
            "name": "janka102",
            "avatar": "https://avatars.githubusercontent.com/u/1645882?v=4"
        },
        {
            "name": "MasterGroosha",
            "avatar": "https://avatars.githubusercontent.com/u/2780044?v=4"
        },
        {
            "name": "octogram-server",
            "avatar": "https://avatars.githubusercontent.com/u/137094628?v=4"
        },
        {
            "name": "acran",
            "avatar": "https://avatars.githubusercontent.com/u/4603809?v=4"
        },
        {
            "name": "slp",
            "avatar": "https://avatars.githubusercontent.com/u/511389?v=4"
        },
        {
            "name": "spagy",
            "avatar": "https://avatars.githubusercontent.com/u/5479401?v=4"
        },
        {
            "name": "yorlov",
            "avatar": "https://avatars.githubusercontent.com/u/1595733?v=4"
        },
        {
            "name": "abcdeiko",
            "avatar": "https://avatars.githubusercontent.com/u/2629879?v=4"
        },
        {
            "name": "kyeongmincho",
            "avatar": "https://avatars.githubusercontent.com/u/9529786?v=4"
        },
        {
            "name": "ruival",
            "avatar": "https://avatars.githubusercontent.com/u/6691547?v=4"
        }
    ]
}